{"greedy":{"greedy":{"currentFile":{"count":1,"lastUpdated":1737320851027}}},"Greedy Algorithm":{"Greedy Algorithm":{"internalLink":{"count":2,"lastUpdated":1737321769406}}},"starting":{"starting":{"currentFile":{"count":1,"lastUpdated":1737320934567}}},"Vertex":{"Vertex":{"internalLink":{"count":1,"lastUpdated":1737320937494}}},"Algorithm":{"Algorithm":{"currentFile":{"count":1,"lastUpdated":1737320996656}}},"algorithm":{"algorithm":{"currentVault":{"count":5,"lastUpdated":1737321938555}}},"Heuristic":{"Heuristic":{"internalLink":{"count":4,"lastUpdated":1737321875586}}},"techniques":{"techniques":{"currentVault":{"count":1,"lastUpdated":1737321119353}}},"solution":{"solution":{"currentVault":{"count":3,"lastUpdated":1737321787870}}},"method":{"method":{"currentVault":{"count":1,"lastUpdated":1737321167411}}},"search":{"search":{"currentVault":{"count":1,"lastUpdated":1737321180061}}},"available":{"available":{"currentVault":{"count":1,"lastUpdated":1737321290088}}},"information":{"information":{"currentVault":{"count":1,"lastUpdated":1737321291584}}},"approximate":{"approximate":{"currentFile":{"count":1,"lastUpdated":1737321399427}}},"algortimi":{"algortimi":{"currentVault":{"count":1,"lastUpdated":1737321810063}}},"heuristic":{"heuristic":{"currentFile":{"count":4,"lastUpdated":1737324560582}}},"either":{"either":{"currentVault":{"count":1,"lastUpdated":1737322503202}}},"theory":{"theory":{"currentFile":{"count":1,"lastUpdated":1737322515002}}},"mathematical":{"mathematical":{"currentVault":{"count":3,"lastUpdated":1737324717162}}},"admissable":{"admissable":{"currentFile":{"count":1,"lastUpdated":1737322965599}}},"algoritmu":{"algoritmu":{"currentVault":{"count":1,"lastUpdated":1737324620183}}},"previous":{"previous":{"currentVault":{"count":2,"lastUpdated":1737324987705}}},"substructure":{"substructure":{"currentFile":{"count":1,"lastUpdated":1737325028627}}},"graph":{"graph":{"currentFile":{"count":1,"lastUpdated":1737376403578}}},"undirected":{"undirected":{"currentFile":{"count":1,"lastUpdated":1737376414450},"currentVault":{"count":3,"lastUpdated":1737379544037}}},"where":{"where":{"currentVault":{"count":1,"lastUpdated":1737376745877}}},"unordered":{"unordered":{"currentVault":{"count":1,"lastUpdated":1737376781022}}},"Undirected":{"Undirected":{"currentFile":{"count":1,"lastUpdated":1737377407001}}},"mama\\n":{"mama\\n":{"currentVault":{"count":3,"lastUpdated":1737378427742}}},"Unconnected graph":{"Unconnected graph":{"internalLink":{"count":1,"lastUpdated":1737379579311}}},"unconnected":{"unconnected":{"currentFile":{"count":1,"lastUpdated":1737379707875}}},"disks":{"disks":{"currentVault":{"count":1,"lastUpdated":1737379724980}}},"transakcij":{"transakcij":{"currentFile":{"count":1,"lastUpdated":1739625620340}}},"spreminjanje":{"spreminjanje":{"currentVault":{"count":1,"lastUpdated":1739627423026}}},"struktur":{"struktur":{"currentVault":{"count":1,"lastUpdated":1739627424379}}},"podatkov":{"podatkov":{"currentFile":{"count":1,"lastUpdated":1739627427347}}},"DBMS":{"DBMS":{"internalLink":{"count":1,"lastUpdated":1739628997473}}},"commited":{"commited":{"currentFile":{"count":3,"lastUpdated":1739629936819}}},"sprememba":{"sprememba":{"currentFile":{"count":1,"lastUpdated":1739630851757}}}}